minotaor/__init__.py
minotaor/minotaor.py
minotaor/version.py
minotaor/data/seq.csv
minotaor-0.2.3.dist-info/licenses/LICENSE
minotaor-0.2.3.dist-info/METADATA
minotaor-0.2.3.dist-info/WHEEL
minotaor-0.2.3.dist-info/top_level.txt
minotaor-0.2.3.dist-info/RECORD
