Metadata-Version: 2.4
Name: minotaor
Version: 0.2.3
Summary: Amino acid sequence annotator
Author: Peter Vegh
License-Expression: MIT
Project-URL: Homepage, https://github.com/Edinburgh-Genome-Foundry/Minotaor
Keywords: biology
License-File: LICENSE
Requires-Dist: pandas
Requires-Dist: biopython
Dynamic: license-file
